{
    "linkset": [
        {
            "anchor": ".",
            "service-desc": [
                {
                    "href": "./ogcapi/",
                    "title": "OGC API Landing Page",
                    "service": "OAPIF",
                    "type": "application/json"
                }
            ],
            "service-doc": [
                {
                    "href": "./ogcapi/",
                    "title": "OGC API Landing Page",
                    "service": "OAPIF",
                    "type": "application/json"
                }
            ]
        }
    ]
}